cpplint.py
cpplint-2.0.1.dist-info/licenses/LICENSE
cpplint-2.0.1.dist-info/METADATA
cpplint-2.0.1.dist-info/WHEEL
cpplint-2.0.1.dist-info/entry_points.txt
cpplint-2.0.1.dist-info/top_level.txt
cpplint-2.0.1.dist-info/RECORD
