Metadata-Version: 2.4
Name: cpplint
Version: 2.0.1
Summary: Check C++ files configurably against Google's style guide
Author: Google Inc., Thibault Kruse, cpplint developers
Author-email: Andrew Davis <theandrewdavis@gmail.com>
Maintainer-email: Aaron Liu <aaronliu0130@gmail.com>, Christian Clauss <cclauss@me.com>, John Vandenberg <jayvdb@gmail.com>
License: BSD-3-Clause
Project-URL: Homepage, https://github.com/cpplint/cpplint
Keywords: c++,cpp,google style,lint
Classifier: Development Status :: 5 - Production/Stable
Classifier: Environment :: Console
Classifier: Intended Audience :: End Users/Desktop
Classifier: License :: Freely Distributable
Classifier: License :: OSI Approved :: BSD License
Classifier: Natural Language :: English
Classifier: Programming Language :: C++
Classifier: Programming Language :: Python :: 3 :: Only
Classifier: Programming Language :: Python :: 3.8
Classifier: Programming Language :: Python :: 3.9
Classifier: Programming Language :: Python :: 3.10
Classifier: Programming Language :: Python :: 3.11
Classifier: Programming Language :: Python :: 3.12
Classifier: Programming Language :: Python :: 3.13
Classifier: Topic :: Software Development :: Quality Assurance
Requires-Python: >=3.8
License-File: LICENSE
Provides-Extra: dev
Requires-Dist: mypy; extra == "dev"
Requires-Dist: parameterized; extra == "dev"
Requires-Dist: pylint>=2.11; extra == "dev"
Requires-Dist: pytest; extra == "dev"
Requires-Dist: pytest-cov; extra == "dev"
Requires-Dist: pytest-timeout; extra == "dev"
Requires-Dist: testfixtures; extra == "dev"
Requires-Dist: tox<5; extra == "dev"
Dynamic: license-file
